hashall/__init__.py
hashall-1.0.3.dist-info/LICENSE
hashall-1.0.3.dist-info/METADATA
hashall-1.0.3.dist-info/WHEEL
hashall-1.0.3.dist-info/top_level.txt
hashall-1.0.3.dist-info/RECORD
