Metadata-Version: 2.1
Name: hashall
Version: 1.0.3
Summary: Sophisticate Hashed Data Structures
Home-page: https://pypi.org/project/hashall/
Author: khiat Mohammed Abderrezzak
Author-email: khiat.dev@gmail.com
License: MIT
Keywords: hash
Classifier: Programming Language :: Python :: 3
Classifier: Operating System :: OS Independent
Classifier: License :: OSI Approved :: MIT License
Requires-Python: >=3.6
License-File: LICENSE
Requires-Dist: word2number (>=1.1)
